[
  {
    "id": "d427ca8a-39c2-469d-b01c-1e7b8fb3dcd1",
    "created_at": "2026-01-18T22:16:34.560460+00:00",
    "profile_name": "Turbo Funk",
    "coffee_analysis": null,
    "user_preferences": "Funky, Thin, Modern, Turbo",
    "reply": "Profile Created: Turbo Funk\nDescription: A modern, experimental profile designed to pull bright, funky shots with a lighter body. It uses a long bloom phase to develop unique flavors and a declining pressure ramp for a quick, clean extraction.\nPreparation: 18g dose, ground medium-fine. Target a 1:2 ratio (36g output) at 92\u00b0C. Total shot time should be around 25-30 seconds, including pre-infusion and bloom.\nWhy This Works: The initial low-flow pre-infusion and extended bloom allow the coffee to saturate evenly and develop complex acidity and funky, fermented notes, especially with light roasts. The subsequent \"Turbo Charge\" phase uses a declining pressure profile to maintain a high flow rate, extracting sweetness while keeping the body light and avoiding bitterness.\nSpecial Notes: Best suited for light roast, naturally processed coffees. A paper filter on the bottom of the portafilter can help enhance clarity.\n\nPROFILE JSON:\n```json\n{\n  \"name\": \"Turbo Funk\",\n  \"author\": \"Gemini Barista\",\n  \"temperature\": 92.0,\n  \"final_weight\": 36.0,\n  \"stages\": [\n    {\n      \"name\": \"Funky Town\",\n      \"key\": \"preinfusion\",\n      \"type\": \"flow\",\n      \"dynamics_points\": [[0, 2], [8, 2]],\n      \"dynamics_over\": \"time\",\n      \"dynamics_interpolation\": \"linear\",\n      \"exit_triggers\": [\n        {\"type\": \"time\", \"value\": 8, \"comparison\": \">=\"}\n      ],\n      \"limits\": []\n    },\n    {\n      \"name\": \"Funky Bloom\",\n      \"key\": \"bloom\",\n      \"type\": \"flow\",\n      \"dynamics_points\": [[0, 0]],\n      \"dynamics_over\": \"time\",\n      \"dynamics_interpolation\": \"none\",\n      \"exit_triggers\": [\n        {\"type\": \"time\", \"value\": 10, \"comparison\": \">=\"}\n      ],\n      \"limits\": []\n    },\n    {\n      \"name\": \"Turbo Charge\",\n      \"key\": \"extraction\",\n      \"type\": \"pressure\",\n      \"dynamics_points\": [[0, 6], [15, 5]],\n      \"dynamics_over\": \"time\",\n      \"dynamics_interpolation\": \"linear\",\n      \"exit_triggers\": [\n        {\"type\": \"weight\", \"value\": 36, \"comparison\": \">=\"}\n      ],\n      \"limits\": [\n        {\"type\": \"flow\", \"value\": 6}\n      ]\n    }\n  ],\n  \"variables\": [],\n  \"accent_color\": \"#FF00FF\"\n}\n```\n",
    "profile_json": {
      "name": "Turbo Funk",
      "author": "Gemini Barista",
      "temperature": 92.0,
      "final_weight": 36.0,
      "stages": [
        {
          "name": "Funky Town",
          "key": "preinfusion",
          "type": "flow",
          "dynamics_points": [
            [
              0,
              2
            ],
            [
              8,
              2
            ]
          ],
          "dynamics_over": "time",
          "dynamics_interpolation": "linear",
          "exit_triggers": [
            {
              "type": "time",
              "value": 8,
              "comparison": ">="
            }
          ],
          "limits": []
        },
        {
          "name": "Funky Bloom",
          "key": "bloom",
          "type": "flow",
          "dynamics_points": [
            [
              0,
              0
            ]
          ],
          "dynamics_over": "time",
          "dynamics_interpolation": "none",
          "exit_triggers": [
            {
              "type": "time",
              "value": 10,
              "comparison": ">="
            }
          ],
          "limits": []
        },
        {
          "name": "Turbo Charge",
          "key": "extraction",
          "type": "pressure",
          "dynamics_points": [
            [
              0,
              6
            ],
            [
              15,
              5
            ]
          ],
          "dynamics_over": "time",
          "dynamics_interpolation": "linear",
          "exit_triggers": [
            {
              "type": "weight",
              "value": 36,
              "comparison": ">="
            }
          ],
          "limits": [
            {
              "type": "flow",
              "value": 6
            }
          ]
        }
      ],
      "variables": [],
      "accent_color": "#FF00FF"
    },
    "image_preview": null
  },
  {
    "id": "aa3e1f11-59f1-41fc-a9c6-05c296ae3e04",
    "created_at": "2026-01-18T21:51:11.576927+00:00",
    "profile_name": "Fruity Funk Fusion",
    "coffee_analysis": null,
    "user_preferences": "Fruitiness, Funky, Thin, Pre-infusion",
    "reply": "Profile Created: Fruity Funk Fusion\nDescription: A multi-stage profile designed to highlight the wild, fruity, and funky notes in light roast coffees. It uses a long, gentle pre-infusion and a blooming phase to develop complex aromatics, followed by a declining pressure phase to ensure a sweet, clean finish with a lighter body.\nPreparation: Dose 18g of a light roast coffee, ground slightly coarser than a typical espresso setting. Target a final liquid weight of 45g. Temperature is set to 92\u00b0C. Total shot time should be around 45-55 seconds, including the pre-infusion and bloom.\nWhy This Works: The extended 15-second low-flow pre-infusion and 10-second zero-flow bloom gently saturate the puck, extracting delicate, volatile compounds without pulling harsh bitters. The declining pressure from 8 to 6 bars during the main extraction prevents over-extraction, reducing bitterness and promoting a sweet, thin-bodied cup that lets the funky fruit notes shine.\nSpecial Notes: A paper filter at the bottom of the basket is recommended to enhance clarity and prevent stalling with finer grinds.\n\nPROFILE JSON:\n```json\n{\n  \"name\": \"Fruity Funk Fusion\",\n  \"author\": \"Gemini Barista\",\n  \"temperature\": 92.0,\n  \"final_weight\": 45.0,\n  \"stages\": [\n    {\n      \"name\": \"Pre-infuse\",\n      \"key\": \"preinfuse\",\n      \"type\": \"flow\",\n      \"dynamics_points\": [\n        [0, 2],\n        [15, 2]\n      ],\n      \"dynamics_over\": \"time\",\n      \"dynamics_interpolation\": \"linear\",\n      \"exit_triggers\": [\n        {\n          \"type\": \"time\",\n          \"value\": 15,\n          \"comparison\": \">=\"\n        }\n      ],\n      \"limits\": []\n    },\n    {\n      \"name\": \"Bloom\",\n      \"key\": \"bloom\",\n      \"type\": \"flow\",\n      \"dynamics_points\": [\n        [0, 0]\n      ],\n      \"dynamics_over\": \"time\",\n      \"dynamics_interpolation\": \"none\",\n      \"exit_triggers\": [\n        {\n          \"type\": \"time\",\n          \"value\": 10,\n          \"comparison\": \">=\"\n        }\n      ],\n      \"limits\": []\n    },\n    {\n      \"name\": \"Ramp\",\n      \"key\": \"ramp\",\n      \"type\": \"pressure\",\n      \"dynamics_points\": [\n        [0, 3],\n        [5, 8]\n      ],\n      \"dynamics_over\": \"time\",\n      \"dynamics_interpolation\": \"linear\",\n      \"exit_triggers\": [\n        {\n          \"type\": \"time\",\n          \"value\": 5,\n          \"comparison\": \">=\"\n        }\n      ],\n      \"limits\": [\n        {\n          \"type\": \"flow\",\n          \"value\": 4\n        }\n      ]\n    },\n    {\n      \"name\": \"Extraction\",\n      \"key\": \"extraction\",\n      \"type\": \"pressure\",\n      \"dynamics_points\": [\n        [0, 8],\n        [20, 6]\n      ],\n      \"dynamics_over\": \"time\",\n      \"dynamics_interpolation\": \"linear\",\n      \"exit_triggers\": [\n        {\n          \"type\": \"weight\",\n          \"value\": 45,\n          \"comparison\": \">=\"\n        }\n      ],\n      \"limits\": []\n    }\n  ],\n  \"accent_color\": \"#FF00FF\"\n}\n```\n",
    "profile_json": {
      "name": "Fruity Funk Fusion",
      "author": "Gemini Barista",
      "temperature": 92.0,
      "final_weight": 45.0,
      "stages": [
        {
          "name": "Pre-infuse",
          "key": "preinfuse",
          "type": "flow",
          "dynamics_points": [
            [
              0,
              2
            ],
            [
              15,
              2
            ]
          ],
          "dynamics_over": "time",
          "dynamics_interpolation": "linear",
          "exit_triggers": [
            {
              "type": "time",
              "value": 15,
              "comparison": ">="
            }
          ],
          "limits": []
        },
        {
          "name": "Bloom",
          "key": "bloom",
          "type": "flow",
          "dynamics_points": [
            [
              0,
              0
            ]
          ],
          "dynamics_over": "time",
          "dynamics_interpolation": "none",
          "exit_triggers": [
            {
              "type": "time",
              "value": 10,
              "comparison": ">="
            }
          ],
          "limits": []
        },
        {
          "name": "Ramp",
          "key": "ramp",
          "type": "pressure",
          "dynamics_points": [
            [
              0,
              3
            ],
            [
              5,
              8
            ]
          ],
          "dynamics_over": "time",
          "dynamics_interpolation": "linear",
          "exit_triggers": [
            {
              "type": "time",
              "value": 5,
              "comparison": ">="
            }
          ],
          "limits": [
            {
              "type": "flow",
              "value": 4
            }
          ]
        },
        {
          "name": "Extraction",
          "key": "extraction",
          "type": "pressure",
          "dynamics_points": [
            [
              0,
              8
            ],
            [
              20,
              6
            ]
          ],
          "dynamics_over": "time",
          "dynamics_interpolation": "linear",
          "exit_triggers": [
            {
              "type": "weight",
              "value": 45,
              "comparison": ">="
            }
          ],
          "limits": []
        }
      ],
      "accent_color": "#FF00FF"
    },
    "image_preview": null
  }
]